source_linkedin_ads/__init__.py
source_linkedin_ads/components.py
source_linkedin_ads/config_migrations.py
source_linkedin_ads/manifest.yaml
source_linkedin_ads/run.py
source_linkedin_ads/source.py
source_linkedin_ads/spec.yaml
source_linkedin_ads/utils.py
airbyte_source_linkedin_ads-5.4.1.dist-info/METADATA
airbyte_source_linkedin_ads-5.4.1.dist-info/WHEEL
airbyte_source_linkedin_ads-5.4.1.dist-info/entry_points.txt
airbyte_source_linkedin_ads-5.4.1.dist-info/RECORD
