Metadata-Version: 2.3
Name: airbyte-source-linkedin-ads
Version: 5.4.1
Summary: Source implementation for Linkedin Ads.
License: MIT
Author: Airbyte
Author-email: contact@airbyte.io
Requires-Python: >=3.10,<3.12
Classifier: License :: OSI Approved :: MIT License
Classifier: Programming Language :: Python :: 3
Classifier: Programming Language :: Python :: 3.10
Classifier: Programming Language :: Python :: 3.11
Requires-Dist: airbyte-cdk (>=6,<7)
Requires-Dist: coverage (>=7.5.3,<8.0.0)
Requires-Dist: pendulum (<3.0.0)
Project-URL: Documentation, https://docs.airbyte.com/integrations/sources/linkedin-ads
Project-URL: Homepage, https://airbyte.com
Project-URL: Repository, https://github.com/airbytehq/airbyte
